[
    {
        "id": 1,
        "tv_channel": "DIGI24 HD",
        "tv_program": [
            "07:00 - Știrile dimineții",
            "11:30 - Paşaport diplomatic",
            "12:00 - Știrile amiezii",
            "13:00 - Știrile amiezii",
            "15:00 - Ştirile Digi24",
            "16:00 - Știrile zilei",
            "18:00 - LIVE",
            "20:00 - Ediție specială",
            "22:00 - Știrile serii",
            "23:00 - Știrile serii",
            "00:00 - Știrile serii",
            "00:50 - Ediție specială",
            "02:30 - Știri ora 22.00",
            "03:00 - Scena deschisă",
            "04:00 - Studio politic",
            "05:00 - Business Club",
            "06:00 - Știrile dimineții"
        ]
    },
    {
        "id": 2,
        "tv_channel": "ANTENA3",
        "tv_program": [
            "07:00 - Ştiri",
            "08:00 - Știrile dimineții",
            "10:00 - Stiri cu Ana Iorga",
            "11:00 - NewsRoom cu Madalina Mihalache",
            "12:00 - Ştiri",
            "13:00 - NewsRoom",
            "14:00 - Ştiri",
            "15:00 - Decisiv",
            "16:30 - România Inteligentă",
            "17:00 - Decisiv",
            "18:00 - News Hour with CNN",
            "19:00 - Top News cu Sabina Iosub si Radu Tudor",
            "20:00 - Subiectiv",
            "21:00 - Exces de putere",
            "23:00 - Ştiri",
            "00:00 - Ştiri",
            "01:00 - Top News cu Sabina Iosub si Radu Tudor , reluare",
            "02:00 - Subiectiv",
            "02:30 - Exces de putere",
            "04:00 - Decisiv cu Catalina Porumbel, reluare",
            "05:00 - News Hour with CNN",
            "06:00 - Știrile dimineții"
        ]
    },
    {
        "id": 3,
        "tv_channel": "B1",
        "tv_program": [
            "08:00 - Bună dimineața, România!",
            "12:00 - Talk B1",
            "15:00 - Politica zilei",
            "18:00 - Bună, România!",
            "20:00 - Special B1",
            "23:00 - Fărădelege - Cu Adriana Stoicescu",
            "00:00 - Bună, România! (R)",
            "01:50 - Politica zilei (R)",
            "03:30 - Fărădelege (R)",
            "04:10 - Special B1 (R)"
        ]
    },
    {
        "id": 7,
        "tv_channel": "PROTV",
        "tv_program": [
            "07:00 - Ştirile Pro Tv",
            "10:30 - Vorbeşte lumea",
            "13:00 - Ştirile Pro Tv",
            "14:00 - Lecţii de viaţă",
            "15:00 - La Maruţă",
            "17:00 - Ştirile Pro Tv",
            "18:00 - Batem palma?",
            "19:00 - Ştirile Pro Tv",
            "20:30 - Românii au talent",
            "00:00 - 57 de secunde 2023 - SUA - SF, Thriller Cu: Morgan Freeman, Josh Hutcherson Nota: 6.4 / Imdb 5.4",
            "02:00 - 24 de ore de viață 2017 - (R) - Africa de Sud, Hong Kong, SUA - Acţiune, SF, Thriller Cu: Paul Anderson (XVIII), Ethan Hawke Nota: 6.4 / Imdb 5.8",
            "03:30 - Doctor de bine",
            "04:00 - Vorbeşte lumea",
            "06:00 - Lecţii de viaţă"
        ]
    },
    {
        "id": 8,
        "tv_channel": "ANTENA1",
        "tv_program": [
            "08:00 - Neatza cu Răzvan şi Dani",
            "12:00 - Observator",
            "14:00 - Mireasa",
            "17:00 - Observator",
            "18:00 - Survivor: Povești din junglă",
            "19:00 - Observator",
            "20:30 - Survivor",
            "23:30 - Power Couple - La bine si la greu",
            "03:00 - Observator",
            "04:00 - Ești mai deștept decât un copil de clasa a V-a?",
            "05:00 - Survivor: Povești din junglă",
            "06:00 - Observator"
        ]
    },
    {
        "id": 4,
        "tv_channel": "TVR1",
        "tv_program": [
            "07:00 - Telejurnal matinal",
            "07:45 - Teleshopping",
            "08:00 - Telejurnal matinal",
            "08:45 - Teleshopping",
            "09:00 - Exclusiv în România",
            "10:00 - Deceniul ascuns",
            "11:00 - Câştigă România!",
            "12:00 - Teleshopping",
            "12:15 - Pofticioşi, la cratiţă!",
            "12:45 - Secretele de la palat • Ep.28 2009 - (R) - Coreea de Sud - Dramă, Istoric, Război Cu: Yo-won Lee, Seong-jo Choi Nota: 9.0 / Imdb 8.5",
            "14:00 - Telejurnal",
            "14:55 - Vorbeşte corect!",
            "15:00 - Opre Roma",
            "15:55 - Etnicity",
            "16:50 - Zi de zi cu părintele Constantin Necula",
            "17:00 - Secretele de la palat • Ep.29 2009 - Coreea de Sud - Dramă, Istoric, Război Cu: Yo-won Lee, Seong-jo Choi Nota: 9.0 / Imdb 8.5",
            "18:15 - Alchimia banilor",
            "18:45 - Breaking fake news",
            "19:45 - Sport",
            "20:00 - Telejurnal",
            "20:55 - Meteo",
            "21:00 - Gala Umorului",
            "22:30 - Vedeta familiei",
            "00:25 - Alchimia banilor",
            "00:55 - Breaking fake news",
            "01:55 - Dincolo de alb şi negru",
            "02:45 - Devreme, despre vreme",
            "03:10 - Exclusiv în România",
            "04:00 - Sport",
            "04:10 - Telejurnal",
            "05:00 - Meteo",
            "05:05 - Tezaur folcloric",
            "05:55 - Imnul României",
            "06:00 - Teleshopping"
        ]
    },
    {
        "id": 5,
        "tv_channel": "TVR2",
        "tv_program": [
            "07:00 - Levintza prezintă",
            "07:30 - Documentar 360° Geo",
            "08:30 - Teleshopping",
            "08:45 - Generaţia Fit",
            "09:25 - România... în bucate",
            "10:00 - Tonomatul de pe 2",
            "11:30 - Teleshopping",
            "12:00 - Telejurnal TVR 2",
            "12:35 - Meteo",
            "12:40 - Sport",
            "13:00 - Cultura minorităţilor",
            "13:30 - Magazin Deutsche Welle",
            "14:00 - Documentar 360° Geo",
            "15:00 - Teleshopping",
            "15:15 - Comisarul Rex: aventuri la Viena • Ep.53 1994 - (R) - Austria, Germania - Acţiune, Crimă, Mister Cu: Tobias Moretti, Reginald von Ravenhorst Nota: 8.8 / Imdb 7.2",
            "16:05 - Forta ideilor",
            "17:00 - Simplu si rural",
            "17:30 - România... în bucate",
            "18:00 - Ora de ştiri",
            "18:40 - Sport",
            "18:50 - E vremea ta!",
            "19:05 - Comisarul Rex: aventuri la Viena • Ep.54 1994 - Austria, Germania - Acţiune, Crimă, Mister Cu: Tobias Moretti, Reginald von Ravenhorst Nota: 8.8 / Imdb 7.2",
            "20:05 - Inimi • Sez.2, Ep.9-10 2021 - Italia - Dramă Cu: Marco Bonini, Carola Stagnaro Nota: 7.9 / Imdb 7.7",
            "23:55 - Magazin Deutsche Welle",
            "00:30 - Levintza prezintă",
            "01:00 - Nostalgia dictaturii 2020 - Romania - Documentar Cu: Ada Milea, Cristian Pârvulescu Nota: 6.6 / Imdb 6.2",
            "02:40 - Ora de ştiri",
            "03:20 - Sport",
            "03:30 - E vremea ta!",
            "03:45 - România... în bucate",
            "04:10 - Istorii de bun gust",
            "05:00 - Forta ideilor",
            "05:50 - Fără prejudecăţi",
            "06:20 - E vremea ta!",
            "06:35 - Sport",
            "06:55 - Imnul României"
        ]
    },
    {
        "id": 9,
        "tv_channel": "Kanal D",
        "tv_program": [
            "07:00 - Secrete de familie 2021 - Turcia - Crimă, Dramă Cu: Kaan Urgancioglu, Pinar Deniz Nota: 8.7 / Imdb 8.2",
            "08:00 - Follow us",
            "10:00 - Casa iubirii",
            "12:00 - Știrile Kanal D",
            "13:00 - În căutarea adevărului",
            "15:00 - Jocul cuvintelor cu Dan Negru",
            "16:30 - Casa iubirii",
            "19:00 - Știrile Kanal D",
            "20:00 - Fata de la fereastră 2021 - Turcia - Dramă Cu: Burcu Biricik, Selma Ergeç Nota: - / Imdb 5.5",
            "22:30 - Răzbunare la Bangkok 2014 - SUA, Marea Britanie, Canada - Acţiune, Dramă Cu: Dolph Lundgren, Markus Waldow Nota: 6.8 / Imdb 5.6",
            "00:30 - Știrile Kanal D",
            "01:30 - Ramo 2020 - (R) - Turcia - Acţiune, Dramă Cu: Murat Yildirim, Esra Bilgiç Nota: 8.1 / Imdb 6.9",
            "04:15 - Casa iubirii",
            "06:30 - Apel la consilier"
        ]
    },
    {
        "id": 10,
        "tv_channel": "Prima TV",
        "tv_program": [
            "07:00 - Exclusiv VIP",
            "09:00 - Iubiri vinovate 2017 - (R) - Chile - Dramă, Romantic Cu: Álvaro Rudolphy, Paola Volpato Nota: - / Imdb 7.3",
            "11:00 - Teleshopping",
            "13:00 - 50/50",
            "14:00 - Focus",
            "16:00 - Exclusiv VIP",
            "18:00 - Focus 18",
            "19:30 - 50/50",
            "22:00 - Cursa iubirii",
            "00:45 - Ion: Blestemul pământului, blestemul iubirii 1980 - (R) - Romania - Dramă, Istoric Cu: Ioana Crăciunescu, Petrică Gheorghiu Nota: 8.4 / Imdb 8.1",
            "02:30 - Exclusiv VIP",
            "04:30 - Iubiri vinovate 2017 - (R) - Chile - Dramă, Romantic Cu: Álvaro Rudolphy, Paola Volpato Nota: - / Imdb 7.3",
            "06:00 - Focus"
        ]
    },
    {
        "id": 11,
        "tv_channel": "TVR3",
        "tv_program": [
            "07:00 - Telematinal",
            "07:55 - Povestea zilei",
            "08:00 - Telematinal",
            "08:55 - Teleshopping",
            "09:00 - Dimineti perfecte",
            "09:55 - Teleshopping",
            "10:00 - Telescoala in limba maghiara",
            "10:55 - Memoria tiparului",
            "11:00 - Toţi împreună",
            "12:50 - Teleshopping",
            "13:05 - Toţi împreună",
            "13:30 - Istoria necunoscută",
            "13:55 - Teleshopping",
            "14:00 - Tableta de sănătate",
            "14:55 - Art pass",
            "15:00 - Picătura de cultură",
            "15:30 - Schiţe urbane",
            "16:00 - Forum economic",
            "16:55 - Teleshopping",
            "17:00 - Telejurnal regional",
            "17:30 - Lumea de aproape",
            "17:55 - Teleshopping",
            "18:00 - TV Retro",
            "19:00 - Provocarea regiunilor",
            "19:55 - Art pass",
            "20:00 - TV Retro",
            "20:30 - TV Retro",
            "21:00 - TV Retro",
            "21:30 - Meseriaşii",
            "21:55 - Memoria tiparului",
            "22:00 - Program preluat de la Televiziunea Publică din Ucraina destinat refugiaţilor",
            "00:00 - TVRetro",
            "00:55 - Memoria tiparului",
            "01:00 - Provocarea regiunilor",
            "01:55 - Art pass",
            "02:00 - TV Retro",
            "02:30 - TV Retro",
            "03:00 - TV Retro",
            "03:30 - Meseriaşii",
            "03:55 - Memoria tiparului",
            "04:00 - Toţi împreună",
            "05:55 - Art pass",
            "06:00 - Program preluat de la Televiziunea Publică din Ucraina destinat refugiaţilor",
            "06:55 - Imnul României"
        ]
    },
    {
        "id": 12,
        "tv_channel": "TVR International",
        "tv_program": [
            "07:00 - Telejurnal matinal",
            "07:45 - Discover Romania",
            "08:00 - Telejurnal matinal",
            "08:50 - Pastila de istorie",
            "09:00 - Dincolo de alb şi negru",
            "09:50 - Drag de România mea!",
            "11:30 - Dialoguri colorate",
            "12:00 - România în lume",
            "13:00 - Lecţia de istorie",
            "14:00 - Telejurnal",
            "14:35 - România... în bucate",
            "15:00 - Forţa ideilor",
            "15:55 - Vorbeşte corect!",
            "16:00 - Exclusiv în România",
            "17:00 - Brilliant",
            "17:30 - Istorii ascunse",
            "18:00 - Telejurnal Moldova",
            "18:45 - Discover Romania",
            "19:00 - Breaking fake news",
            "20:00 - Telejurnal",
            "20:55 - Zi de zi cu părintele Constantin Necula",
            "21:00 - Gala Umorului",
            "22:15 - Jurnal Cultural",
            "23:00 - Graniţa morţii 2020 - (R) - Romania - Documentar Cu: Avram Iclozan, Tudor Morgovan Nota: 7.5 / Imdb 8.3",
            "00:45 - Duelul pianelor",
            "02:20 - Reţeaua de idoli",
            "03:10 - Telejurnal",
            "04:00 - Un doctor pentru dumneavoastră",
            "05:00 - Exclusiv în România",
            "05:55 - Imnul României",
            "06:00 - Breaking fake news",
            "06:50 - Discover Romania"
        ]
    },
    {
        "id": 13,
        "tv_channel": "Digi 24",
        "tv_program": [
            "07:00 - Știrile dimineții",
            "11:30 - Paşaport diplomatic",
            "12:00 - Știrile amiezii",
            "13:00 - Știrile amiezii",
            "15:00 - Ştirile Digi24",
            "16:00 - Știrile zilei",
            "18:00 - LIVE",
            "20:00 - Ediție specială",
            "22:00 - Știrile serii",
            "23:00 - Știrile serii",
            "00:00 - Știrile serii",
            "00:50 - Ediție specială",
            "02:30 - Știri ora 22.00",
            "03:00 - Scena deschisă",
            "04:00 - Studio politic",
            "05:00 - Business Club",
            "06:00 - Știrile dimineții"
        ]
    },
    {
        "id": 14,
        "tv_channel": "PROCINEMA",
        "tv_program": [
            "08:30 - Misterul lui Hailey Dean: Rețeta pentru crimă 2019 - (R) - SUA - Crimă, Dramă, Mister Cu: Kellie Martin, Viv Leacock Nota: 6.6 / Imdb 6.8",
            "10:15 - La bloc 2002 - (R) - Romania - Comedie Cu: Dragos Mostenescu, Dana Rogoz Nota: 8.4 / Imdb 6.2",
            "12:30 - Peştişorul magic 2017 - (R) - SUA - Familie Cu: Martin Klebba, Robert Carradine Nota: - / Imdb 5.2",
            "14:15 - Ediția despre iubire 2022 - Romantic Cu: Alicia Josipovic, Luke Humphrey Nota: - / Imdb 5.8",
            "16:15 - Cazurile lui Ruby Herring: Martorul mut 2019 - SUA - Crimă, Mister Cu: Taylor Cole, Stephen Huszar Nota: 7.2 / Imdb 6.3",
            "18:15 - La bloc 2002 - Romania - Comedie Cu: Dragos Mostenescu, Dana Rogoz Nota: 8.4 / Imdb 6.2",
            "22:15 - Praf si pulbere: Dreptate pe cont propriu 2007 - SUA - Acţiune, Crimă, Dramă Cu: Kevin Sorbo, Haley Ramm Nota: 6.2 / Imdb 4.8",
            "00:15 - Arta hoției 2013 - (R) - Canada, SUA - Comedie, Crimă Cu: Jay Baruchel, Kurt Russell Nota: 6.4 / Imdb 6.3",
            "02:00 - Apropo Tv",
            "03:00 - La Maruţă",
            "04:45 - La bloc 2002 - (R) - Romania - Comedie Cu: Dragos Mostenescu, Dana Rogoz Nota: 8.4 / Imdb 6.2",
            "05:45 - Batem palma?"
        ]
    },
    {
        "id": 15,
        "tv_channel": "ANTENA STARS",
        "tv_program": [
            "08:00 - Meniu de vedetă",
            "08:30 - Mireasa - Capriciile Iubirii",
            "11:00 - Știrile Antena Stars",
            "12:30 - Mireasa",
            "13:30 - Viaţa Fără Filtru",
            "16:00 - Acces direct",
            "19:00 - Mireasa - Capriciile Iubirii",
            "21:30 - Xtra Night Show",
            "00:00 - Acces direct",
            "02:45 - Xtra Night Show",
            "04:30 - Știrile Antena Stars",
            "06:00 - Lumea Nevăzută"
        ]
    },
    {
        "id": 16,
        "tv_channel": "National Geographic",
        "tv_program": [
            "07:00 - Clipe de coşmar",
            "08:00 - Clipe de coşmar",
            "09:00 - Salvatori pe drumuri înghețate",
            "10:00 - Salvatori pe drumuri înghețate",
            "11:00 - Prognoze îngrijorătoare",
            "12:00 - Traficanți pe aeroport",
            "13:00 - Traficanți pe aeroport",
            "14:00 - Traficanți pe aeroport",
            "15:00 - Dezastre în aer",
            "16:00 - Dezastre în aer",
            "17:00 - Aeroportul din Toronto",
            "18:00 - Inginerie abandonată",
            "19:00 - Salvatori pe drumuri înghețate",
            "20:00 - Istoria interzisă",
            "21:00 - Roma",
            "22:00 - Comori pierdute ale Romei",
            "23:00 - Ginghis Han",
            "00:00 - Dezastre în aer",
            "01:00 - Ilegal cu Mariana van Zeller",
            "02:00 - Inginerie abandonată",
            "03:00 - S.O.S. Mașini clasice",
            "04:00 - Ilegal cu Mariana van Zeller",
            "05:00 - Inginerie abandonată",
            "06:00 - Dezastre în aer"
        ]
    },
    {
        "id": 17,
        "tv_channel": "TVR Cultural",
        "tv_program": [
            "07:00 - Grădini de vis: geometrie, artă, viaţă (R)",
            "07:30 - Intrare liberă (R)",
            "09:00 - Jurnal Cultural (R)",
            "10:00 - Classy Jukebox",
            "12:00 - Concert de prânz",
            "13:00 - Jurnal Cultural",
            "13:05 - Istorii cu tâlc",
            "14:00 - Portret de artist (R)",
            "14:30 - Cultura minorităţilor",
            "15:00 - Tempo Rubato (R)",
            "16:00 - Classy Jukebox",
            "16:30 - ArtMakers (R)",
            "17:30 - Piper pe limba",
            "18:30 - Eveniment TVR Cultural",
            "20:00 - Tineri muzicieni în Festivalul Enescu",
            "21:00 - Jurnal Cultural",
            "22:00 - Graniţa morţii",
            "23:45 - Nocturne",
            "00:30 - Concert de prânz (R)",
            "01:15 - Jurnal Cultural (R)",
            "02:05 - Piper pe limba (R)",
            "02:55 - Graniţa morţii (R)",
            "04:40 - lnterviurile TVR Cultural (R)",
            "05:05 - Classy Jukebox (R)",
            "06:55 - Imnul României"
        ]
    },
    {
        "id": 20,
        "tv_channel": "HBO",
        "tv_program": [
            "07:40 - Superman 2025 - SUA - Acţiune, Aventuri, Fantastic Cu: Nicholas Hoult, Isabela Merced Nota: 6.2 / Imdb 7.1",
            "09:50 - Insula câinilor 2018 - Germania, SUA - Animaţie, Aventuri, Comedie Cu: Bryan Cranston, Koyu Rankin Nota: 7.3 / Imdb 7.8",
            "11:35 - Pe platourile de filmare • Sez.23, Ep.4",
            "12:05 - Farsa 2022 - SUA - Comedie, Thriller Cu: Rita Moreno, Connor Kalopsis Nota: - / Imdb 5.4",
            "13:40 - Marțianul 2015 - SUA - Acţiune, Aventuri, SF Cu: Matt Damon, Kristen Wiig Nota: 8.2 / Imdb 8.0",
            "16:00 - Brokerii apocalipsei 2015 - SUA - Biografic, Dramă Cu: Christian Bale, Steve Carell Nota: 7.6 / Imdb 7.8",
            "18:10 - Nostalgie 2024 - Canada - Comedie, Dramă Cu: Diane Kruger, Richard Gere Nota: 6.8 / Imdb 4.8",
            "21:55 - Sfârșitul 2024 - Danemarca, Irlanda, Germania, Italia, Marea Britanie, SUA, Suedia - Dramă, Fantastic, Muzical Cu: Tilda Swinton, Michael Shannon Nota: 6.3 / Imdb 5.4",
            "00:20 - Angajamentul 2023 - Marea Britanie, Spania - Acţiune, Crimă, Thriller Cu: Jake Gyllenhaal, Dar Salim Nota: 7.9 / Imdb 7.5",
            "02:20 - Dragoste, minciuni și sânge 2024 - Marea Britanie, SUA - Acţiune, Crimă, Romantic Cu: Kristen Stewart, Ed Harris Nota: 5.8 / Imdb 6.6",
            "04:05 - Saga Amurg: Zori de Zi - Partea I 2011 - SUA - Dramă, Fantastic, Romantic Cu: Kristen Stewart, Robert Pattinson Nota: 7.3 / Imdb 5.0"
        ]
    },
    {
        "id": 21,
        "tv_channel": "HBO_2",
        "tv_program": [
            "07:00 - Alita: Îngerul războinic 2019 - SUA, Canada, Argentina - Acţiune, Aventuri, Dragoste Cu: Jennifer Connelly, Rosa Salazar Nota: 8.1 / Imdb 7.3",
            "08:57 - Monștri contra extratereștri: Dovlecii mutanți 2009 - SUA - Acţiune, Animaţie, Aventuri Cu: Reese Witherspoon, Seth Rogen Nota: 7.5 / Imdb 6.3",
            "09:24 - Emma. 2020 - Marea Britanie - Comedie, Dramă Cu: Anya Taylor-Joy, Josh O'Connor Nota: 7.0 / Imdb 6.7",
            "11:24 - Wonka 2023 - SUA, Canada, Irlanda, Marea Britanie, Australia, Franta - Aventuri, Comedie, Familie Cu: Timothée Chalamet, Olivia Colman Nota: 7.3 / Imdb 6.9",
            "13:16 - Tornade 2024 - SUA - Acţiune, Aventuri, Thriller Cu: Glen Powell, Maura Tierney Nota: 6.7 / Imdb 6.5",
            "15:15 - Cei rămași • Sez.2, Ep.7 2014 - SUA - Dramă, Fantastic, Mister Cu: Michael Gaston, Margaret Qualley Nota: 7.7 / Imdb 8.3",
            "16:11 - King Kong 2005 - SUA - Acţiune, Aventuri, Romantic Cu: Jack Black, Adrien Brody Nota: 8.0 / Imdb 7.2",
            "19:11 - Ajunul Crăciunului în Țara Minunilor 2024 - Marea Britanie - Animaţie, Familie, Fantastic Cu: Gerard Butler, Emilia Clarke Nota: - / Imdb 6.3",
            "20:32 - Terenul de joacă 2024 - Slovenia - Aventuri, Dramă, Familie Cu: Kaja Zabret, Kaja Sustar Nota: - / Imdb 6.5",
            "23:39 - Baby Driver: Calc-o şi fugi! 2017 - Marea Britanie, SUA - Acţiune, Crimă, Muzical Cu: Ansel Elgort, Jon Bernthal Nota: 7.5 / Imdb 7.5",
            "01:27 - Cutia muzicală - Happy and you know it",
            "02:43 - Mickey 17 2025 - SUA - Aventuri, Comedie, Fantastic Cu: Robert Pattinson, Toni Collette Nota: 6.4 / Imdb 6.7",
            "04:55 - Don Q 2023 - SUA - Comedie, Crimă, Dramă Cu: Armand Assante, Chuck Zito Nota: 6.0 / Imdb 4.4",
            "06:38 - Dragoni: Darul Furiei Nopții 2011 - SUA - Animaţie, Aventuri, Familie Cu: Jay Baruchel, Gerard Butler Nota: 8.4 / Imdb 7.4"
        ]
    },
    {
        "id": 25,
        "tv_channel": "FilmNow",
        "tv_program": [
            "07:55 - Viață de stafie 1988 - SUA - Comedie, Fantastic, Horror Cu: Alec Baldwin, Michael Keaton Nota: 7.5 / Imdb 7.4",
            "09:30 - Stăpânul inelelor: Întoarcerea regelui 2003 - SUA - Acţiune, Aventuri, Fantastic Cu: Ian McKellen, Elijah Wood Nota: 8.9 / Imdb 9.0",
            "12:40 - Victoria și Abdul 2017 - SUA, Marea Britanie - Biografic, Dramă, Istoric Cu: Judi Dench, Ali Fazal Nota: 7.6 / Imdb 6.8",
            "14:25 - Marea provocare: Le Mans ’66 2019 - SUA - Acţiune, Biografic, Dramă Cu: Christian Bale, Matt Damon Nota: 8.4 / Imdb 8.1",
            "16:50 - Mereu dragostea 2022 - SUA - Dramă, Romantic Cu: Autumn Reeser, Tyler Hynes Nota: - / Imdb 6.8",
            "18:15 - O zi minunată în cartier 2019 - SUA, China - Biografic, Dramă Cu: Tom Hanks, Matthew Rhys Nota: 7.0 / Imdb 7.2",
            "21:55 - Hit Man 2023 - SUA - Acţiune, Comedie Cu: Glen Powell, Adria Arjona Nota: 7.0 / Imdb 6.8",
            "23:45 - Greu de ucis 4 2007 - SUA - Acţiune, Crimă, Thriller Cu: Timothy Olyphant, Jeffrey Wright Nota: 7.9 / Imdb 7.1",
            "01:50 - Prometheus 2012 - SUA - Acţiune, Horror, SF Cu: Michael Fassbender, Noomi Rapace Nota: 7.2 / Imdb 7.0",
            "03:50 - Crima este a mea 2023 - Franta - Comedie, Crimă, Dramă Cu: Nadia Tereszkiewicz, Rebecca Marder Nota: 6.7 / Imdb 6.5",
            "05:30 - Homefront: Orașul fără legi 2013 - SUA - Acţiune, Crimă, Thriller Cu: James Franco, Jason Statham Nota: 7.7 / Imdb 6.5"
        ]
    },
    {
        "id": 26,
        "tv_channel": "Atomic-TV",
        "tv_program": []
    },
    {
        "id": 27,
        "tv_channel": "ZU-TV",
        "tv_program": [
            "07:00 - ZUnrise",
            "08:00 - ZU News",
            "08:02 - ZUnrise",
            "10:00 - Hitman Hot 10",
            "11:00 - BIG IN",
            "12:00 - Torpedoul lui Morar + Eat, Sleep, ZU, Repeat",
            "13:00 - Eat, Sleep, ZU, Repeat",
            "14:00 - Celebrity Playlist",
            "15:00 - Eat, Sleep, ZU, Repeat",
            "16:00 - ZU News",
            "16:02 - Torpedoul lui Morar + Eat, Sleep, ZU, Repeat",
            "17:00 - Face 2 Face",
            "18:00 - Torpedoul lui Morar + Eat, Sleep, ZU, Repeat",
            "19:00 - Eat, Sleep, ZU, Repeat",
            "20:00 - BIG IN",
            "21:00 - K-POP",
            "22:00 - Torpedoul lui Morar + Eat, Sleep, ZU, Repeat",
            "23:00 - Eat, Sleep, ZU, Repeat",
            "00:00 - ZU News",
            "00:02 - ZUeet Dreams",
            "06:00 - Eat, Sleep, ZU, Repeat"
        ]
    },
    {
        "id": 28,
        "tv_channel": "MUSIC-CHANNEL",
        "tv_program": [
            "09:00 - 3 Play",
            "09:15 - Morning Mix",
            "10:00 - Today's Hitlist - TOP 10",
            "11:00 - 11 Vids we're loving right now",
            "12:00 - Versus",
            "12:30 - Hot + Hits",
            "13:00 - Hitlist Romania",
            "15:00 - Hot+Hits",
            "16:30 - Versus",
            "17:00 - Get fresh! - TODAY'S HOTTEST 5",
            "17:30 - Social Media Chart",
            "18:00 - Today's Hot Girls",
            "19:05 - Beats and massive R'N'B Hits",
            "20:00 - Hot + Hits",
            "20:30 - 3 Play",
            "20:45 - Hot+Hits",
            "21:00 - DON'T STOP THE PARTY!",
            "23:00 - Club Zone",
            "00:00 - DON'T STOP THE PARTY!",
            "06:00 - Morning Mix"
        ]
    },
    {
        "id": 29,
        "tv_channel": "KISS-TV",
        "tv_program": [
            "07:00 - Kiss & Snooze",
            "10:00 - Kiss Top 40 Cu Andreea Berghea",
            "12:00 - Kiss Me @ Noon",
            "13:00 - Kiss After School",
            "15:00 - Kiss Cinema",
            "16:00 - Kiss The Weekend",
            "19:00 - Kiss Party Starter",
            "21:00 - Kiss Cinema",
            "22:00 - Kiss In The Club",
            "02:00 - Kiss By Night"
        ]
    },
    {
        "id": 30,
        "tv_channel": "TVR Folclor",
        "tv_program": [
            "07:00 - Zestrea muzicală",
            "08:50 - Etnografica",
            "09:00 - Muzica regiunilor",
            "11:00 - Tezaur folcloric",
            "12:00 - Scena românilor",
            "14:00 - Cântec românesc",
            "15:50 - Etnografica",
            "16:00 - Mostenirea cantecului",
            "18:00 - De la sate adunate",
            "19:00 - Tezaur folcloric",
            "20:00 - Ora de aur",
            "21:00 - Scena românilor",
            "22:50 - Etnografica",
            "23:00 - Cu lăutarii după mine",
            "00:00 - Muzică tradiţională",
            "06:55 - Imnul României"
        ]
    },
    {
        "id": 80,
        "tv_channel": "ETNO TV",
        "tv_program": [
            "07:30 - Cântece pentru cei dragi",
            "08:30 - Matinali și populari",
            "11:00 - Cântece pentru cei dragi / Teleshopping",
            "13:00 - Bijuterii TV - Teleshopping",
            "15:00 - Cantece pentru cei dragi / Teleshopping",
            "16:00 - Sănătate înainte de toate",
            "17:00 - Cântece pentru cei dragi",
            "18:00 - Cântece pentru cei dragi",
            "20:00 - Cântec din suflet de roman",
            "22:00 - Dor Călător",
            "01:30 - Cântece pentru cei dragi",
            "04:00 - Matinali și populari",
            "06:30 - Sănătate înainte de toate"
        ]
    },
    {
        "id": 31,
        "tv_channel": "REALITATEA",
        "tv_program": [
            "07:00 - Plus Matinal",
            "10:00 - Realitatea zilei",
            "12:00 - Newsroom",
            "14:00 - Raport de zi",
            "16:00 - Deschide lumea",
            "17:00 - Day time news",
            "18:00 - Ediție specială",
            "20:00 - Primetime news",
            "22:00 - Ediție specială",
            "23:00 - Jurnal",
            "00:00 - Ediție specială",
            "02:00 - Primetime news",
            "03:00 - Raport de zi",
            "05:00 - Jurnal"
        ]
    },
    {
        "id": 32,
        "tv_channel": "PRIMA-NEWS",
        "tv_program": [
            "07:00 - Sistemul Medikal",
            "08:00 - Proiect De Tara",
            "09:00 - Head-Uri Live",
            "09:05 - Proiect De Tara",
            "10:00 - Head-Uri Live",
            "10:05 - Proiect De Tara",
            "11:00 - Head-Uri Live",
            "11:05 - Educatie Cu Profit",
            "12:00 - Head-Uri Live",
            "12:05 - Profit Live",
            "13:00 - Head-Uri Live",
            "13:05 - Viitor Pt Romania",
            "14:00 - Head-Uri Live",
            "14:05 - Viitor Pt Romania",
            "15:00 - Medika Antidrog",
            "16:00 - Focus 14 Inregistrat",
            "18:00 - Prima News Debate",
            "20:00 - Academia De Guvernanta",
            "21:00 - Povesti Sanatoase",
            "22:00 - Cu Iosif Pe Coclauri",
            "00:00 - Viitor Pt Romania",
            "02:00 - Prima News Debate",
            "04:00 - Povesti Sanatoase",
            "05:00 - Cu Iosif Pe Coclauri"
        ]
    },
    {
        "id": 33,
        "tv_channel": "EURO-NEWS",
        "tv_program": [
            "07:00 - Buna dimineata Romania",
            "07:50 - România frumoasă",
            "08:00 - Buna dimineata Romania",
            "08:50 - Euronews World",
            "09:00 - Buna dimineata Romania",
            "09:50 - Trăiești bine!",
            "10:00 - Euronews",
            "10:50 - Euronews Travel",
            "11:00 - Euronews",
            "11:50 - Euronews Culture",
            "12:00 - Euronews",
            "12:30 - Suuper Special",
            "13:00 - Euronews",
            "13:50 - Euronews Next",
            "14:00 - Euronews",
            "14:30 - Euronews Special",
            "15:00 - Retrospectiva politica",
            "15:30 - UPB",
            "16:00 - Euronews",
            "16:50 - Euronews Travel",
            "17:00 - Euronews",
            "17:50 - Euronews Culture",
            "18:00 - Euronews",
            "18:30 - Super Team Romania",
            "19:00 - Romania lui Vitalie",
            "20:00 - Romania lui Vitalie",
            "20:50 - Euronews world",
            "21:00 - Cult",
            "21:30 - Euronews Special",
            "22:00 - Euronews",
            "22:30 - Retrospectiva Euronews Politica",
            "23:00 - Euronews",
            "23:30 - Retrospectiva Filme",
            "00:00 - România Frumoasă",
            "01:00 - România lui Vitalie (R)",
            "02:00 - România lui Vitalie (R)",
            "02:50 - Euronews Next",
            "03:00 - România (R)",
            "03:50 - Euronews My Europe",
            "04:00 - Euronews (R)",
            "04:50 - Euronews Green",
            "05:00 - Euronews Travel",
            "05:15 - Traiesti Bine!",
            "05:30 - Euronews Culture",
            "06:00 - Euronews (R)",
            "06:50 - Euronews World"
        ]
    },
    {
        "id": 34,
        "tv_channel": "CNN-LIVE",
        "tv_program": [
            "07:00 - The Story Is: With Elex Michaelson",
            "09:00 - CNN Newsroom",
            "10:00 - CNN Newsroom",
            "11:00 - Amanpour",
            "12:00 - Early Start with Rahel Solomon",
            "13:00 - CNN This Morning",
            "14:00 - CNN News Central",
            "15:30 - World Sport",
            "16:00 - Connect the World",
            "16:45 - World Sport",
            "17:00 - Connect the World",
            "18:00 - One World",
            "19:00 - One World",
            "20:00 - Amanpour",
            "21:00 - Isa Soares Tonight",
            "22:00 - What We Know with Max Foster",
            "23:00 - Quest Means Business",
            "00:30 - World Sport",
            "01:00 - The Brief with Jim Sciutto",
            "02:00 - Erin Burnett OutFront",
            "03:00 - Anderson Cooper 360",
            "04:00 - The Source with Kaitlan Collins",
            "05:00 - CNN NewsNight"
        ]
    },
    {
        "id": 35,
        "tv_channel": "BBC-NEWS",
        "tv_program": []
    },
    {
        "id": 36,
        "tv_channel": "CBS-REALITY",
        "tv_program": []
    },
    {
        "id": 38,
        "tv_channel": "PRS-1",
        "tv_program": [
            "08:00 - Fotbal Liga I: Fcsb - Otelul Galati",
            "10:00 - Fotbal Spania: Betis - Villarreal",
            "12:00 - Fotbal Liga I: Fcsb - U Craiova",
            "14:00 - Fotbal Spania: Getafe - Valencia",
            "16:00 - Fotbal Liga I: Dinamo - Rapid",
            "18:00 - Fotbal Spania: Atletico - Alaves",
            "20:00 - Fotbal Liga I: Fcsb - Uta",
            "22:00 - Direct Spania: Levante - Elche",
            "00:00 - Fotbal Liga I: Dinamo - Cfr Cluj",
            "02:00 - Fotbal Spania: Real Sociedad - Barcelona",
            "04:00 - Fotbal Liga I: Dinamo - Csikszereda",
            "06:00 - Fotbal Spania: Mallorca - Bilbao"
        ]
    },
    {
        "id": 39,
        "tv_channel": "PRS-2",
        "tv_program": [
            "08:00 - Fotbal Liga I: Fcsb - Otelul Galati",
            "10:00 - Fotbal Spania: Betis - Villarreal",
            "12:00 - Fotbal Liga I: Fcsb - U Craiova",
            "14:00 - Fotbal Spania: Getafe - Valencia",
            "16:00 - Fotbal Liga I: Dinamo - Rapid",
            "18:00 - Fotbal Spania: Atletico - Alaves",
            "20:00 - Fotbal Liga I: Fcsb - Uta",
            "22:00 - Direct Spania: Levante - Elche",
            "00:00 - Fotbal Liga I: Dinamo - Cfr Cluj",
            "02:00 - Fotbal Spania: Real Sociedad - Barcelona",
            "04:00 - Fotbal Liga I: Dinamo - Csikszereda",
            "06:00 - Fotbal Spania: Mallorca - Bilbao"
        ]
    },
    {
        "id": 40,
        "tv_channel": "ER1",
        "tv_program": [
            "07:30 - Tenis: GrandSlam - Australian Open",
            "09:30 - Tenis: GrandSlam - Australian Open",
            "12:00 - Tenis: GrandSlam - Australian Open",
            "15:30 - Biatlon: Cupa Mondială - Nove Mesto - Individual Masculin",
            "16:30 - Schi alpin: Cupa Mondială - Kitzbühel - Super G Masculin",
            "18:00 - Sanie: Cupa Mondială - Oberhof",
            "18:30 - Sanie: Cupa Mondială - Oberhof",
            "19:00 - Biatlon: Cupa Mondială - Nove Mesto - Individual Feminin",
            "21:00 - Tenis",
            "23:00 - Schi alpin: Cupa Mondială - Kitzbühel - Super G Masculin",
            "00:00 - Navigație: SailGP Perth",
            "01:00 - Tenis: GrandSlam - Australian Open",
            "02:30 - Tenis: GrandSlam - Australian Open",
            "05:30 - Tenis: GrandSlam - Australian Open"
        ]
    },
    {
        "id": 41,
        "tv_channel": "ER2",
        "tv_program": [
            "07:30 - Tenis: GrandSlam - Australian Open",
            "10:00 - Tenis: GrandSlam - Australian Open",
            "12:00 - Schi alpin: Cupa Mondială - Kitzbühel - Super G Masculin",
            "14:15 - Schi acrobatic: Cupa Mondială - Veysonnaz - Schi cross",
            "15:30 - Schi fond: Cupa Mondială - Goms - Sprint pe echipe stil liber Mixt",
            "16:30 - Sporturi de iarnă: Cupa Mondială - Altenberg",
            "17:00 - Biatlon: Cupa Mondială - Nove Mesto - Individual Masculin",
            "18:00 - Schi alpin: Cupa Mondială - Kitzbühel - Super G Masculin",
            "19:00 - Tenis: GrandSlam - Australian Open",
            "20:00 - Tenis: GrandSlam - Australian Open",
            "21:00 - Schi alpin: Cupa Mondială - Kitzbühel - Super G Masculin",
            "22:00 - Biatlon: Cupa Mondială - Nove Mesto - Individual Feminin",
            "23:00 - Golf: Circuitul PGA - American Express",
            "02:00 - Biatlon: Cupa Mondială - Nove Mesto - Individual Feminin",
            "02:30 - Tenis: GrandSlam - Australian Open",
            "05:30 - Tenis: GrandSlam - Australian Open"
        ]
    },
    {
        "id": 42,
        "tv_channel": "CARTOON",
        "tv_program": [
            "07:00 - Minunata și năstrușnica lume a lui Gumball • Ep.1",
            "07:10 - Minunata și năstrușnica lume a lui Gumball • Ep.1",
            "07:30 - Uimitoarea lume a lui Gumball • Ep.4 2011 - Marea Britanie, Irlanda, SUA - Animaţie, Comedie, Familie Cu: Kyla Rae Kowalewski, Hugo Harold-Harrison Nota: 8.8 / Imdb 8.4",
            "07:40 - Uimitoarea lume a lui Gumball • Ep.4 2011 - Marea Britanie, Irlanda, SUA - Animaţie, Comedie, Familie Cu: Kyla Rae Kowalewski, Hugo Harold-Harrison Nota: 8.8 / Imdb 8.4",
            "07:55 - Uimitoarea lume a lui Gumball • Ep.4 2011 - Marea Britanie, Irlanda, SUA - Animaţie, Comedie, Familie Cu: Kyla Rae Kowalewski, Hugo Harold-Harrison Nota: 8.8 / Imdb 8.4",
            "08:05 - Uimitoarea lume a lui Gumball • Ep.4 2011 - Marea Britanie, Irlanda, SUA - Animaţie, Comedie, Familie Cu: Kyla Rae Kowalewski, Hugo Harold-Harrison Nota: 8.8 / Imdb 8.4",
            "08:25 - Minunata și năstrușnica lume a lui Gumball • Ep.1",
            "08:35 - Minunata și năstrușnica lume a lui Gumball • Ep.1",
            "08:55 - Uimitoarea lume a lui Gumball • Ep.4 2011 - Marea Britanie, Irlanda, SUA - Animaţie, Comedie, Familie Cu: Kyla Rae Kowalewski, Hugo Harold-Harrison Nota: 8.8 / Imdb 8.4",
            "09:05 - Uimitoarea lume a lui Gumball • Ep.4 2011 - Marea Britanie, Irlanda, SUA - Animaţie, Comedie, Familie Cu: Kyla Rae Kowalewski, Hugo Harold-Harrison Nota: 8.8 / Imdb 8.4",
            "09:25 - Haideți tineri titani! • Ep.2 2013 - SUA - Acţiune, Animaţie, Comedie Cu: Tara Strong, Hynden Walch Nota: 5.8 / Imdb 5.8",
            "09:35 - Haideți tineri titani! • Ep.2 2013 - SUA - Acţiune, Animaţie, Comedie Cu: Tara Strong, Hynden Walch Nota: 5.8 / Imdb 5.8",
            "09:50 - Craig și dumbrava • Ep.6",
            "10:00 - Craig și dumbrava • Ep.6",
            "10:15 - Craig și dumbrava • Ep.6",
            "10:25 - Craig și dumbrava • Ep.6",
            "10:45 - Lana Barbălungă • Ep.1",
            "10:55 - Lana Barbălungă • Ep.1",
            "11:10 - Minunata și năstrușnica lume a lui Gumball • Ep.1",
            "11:25 - Minunata și năstrușnica lume a lui Gumball • Ep.1",
            "11:40 - Uimitoarea lume a lui Gumball • Ep.6 2011 - Marea Britanie, Irlanda, SUA - Animaţie, Comedie, Familie Cu: Kyla Rae Kowalewski, Hugo Harold-Harrison Nota: 8.8 / Imdb 8.4",
            "11:50 - Uimitoarea lume a lui Gumball • Ep.6 2011 - Marea Britanie, Irlanda, SUA - Animaţie, Comedie, Familie Cu: Kyla Rae Kowalewski, Hugo Harold-Harrison Nota: 8.8 / Imdb 8.4",
            "12:00 - Uimitoarea lume a lui Gumball • Ep.6 2011 - Marea Britanie, Irlanda, SUA - Animaţie, Comedie, Familie Cu: Kyla Rae Kowalewski, Hugo Harold-Harrison Nota: 8.8 / Imdb 8.4",
            "12:20 - Uimitoarea lume a lui Gumball • Ep.6 2011 - Marea Britanie, Irlanda, SUA - Animaţie, Comedie, Familie Cu: Kyla Rae Kowalewski, Hugo Harold-Harrison Nota: 8.8 / Imdb 8.4",
            "12:30 - Uimitoarea lume a lui Gumball • Ep.6 2011 - Marea Britanie, Irlanda, SUA - Animaţie, Comedie, Familie Cu: Kyla Rae Kowalewski, Hugo Harold-Harrison Nota: 8.8 / Imdb 8.4",
            "12:45 - Uimitoarea lume a lui Gumball • Ep.6 2011 - Marea Britanie, Irlanda, SUA - Animaţie, Comedie, Familie Cu: Kyla Rae Kowalewski, Hugo Harold-Harrison Nota: 8.8 / Imdb 8.4",
            "12:55 - Uimitoarea lume a lui Gumball • Ep.6 2011 - Marea Britanie, Irlanda, SUA - Animaţie, Comedie, Familie Cu: Kyla Rae Kowalewski, Hugo Harold-Harrison Nota: 8.8 / Imdb 8.4",
            "13:15 - Haideți tineri titani! • Ep.2 2013 - SUA - Acţiune, Animaţie, Comedie Cu: Tara Strong, Hynden Walch Nota: 5.8 / Imdb 5.8",
            "13:25 - Haideți tineri titani! • Ep.2 2013 - SUA - Acţiune, Animaţie, Comedie Cu: Tara Strong, Hynden Walch Nota: 5.8 / Imdb 5.8",
            "13:40 - Clarence • Ep.2 2013 - SUA - Animaţie, Comedie, Familie Cu: Anastasia James, Damien C. Haas Nota: 6.9 / Imdb 6.9",
            "13:50 - Clarence • Ep.2 2013 - SUA - Animaţie, Comedie, Familie Cu: Anastasia James, Damien C. Haas Nota: 6.9 / Imdb 6.9",
            "14:10 - Clarence • Ep.2 2013 - SUA - Animaţie, Comedie, Familie Cu: Anastasia James, Damien C. Haas Nota: 6.9 / Imdb 6.9",
            "14:20 - Clarence • Ep.2 2013 - SUA - Animaţie, Comedie, Familie Cu: Anastasia James, Damien C. Haas Nota: 6.9 / Imdb 6.9",
            "14:35 - Craig și dumbrava • Ep.3",
            "14:45 - Craig și dumbrava • Ep.3",
            "14:55 - Craig și dumbrava • Ep.3",
            "15:15 - Minunata și năstrușnica lume a lui Gumball • Ep.1",
            "15:25 - Minunata și năstrușnica lume a lui Gumball • Ep.1",
            "15:40 - Uimitoarea lume a lui Gumball • Ep.1 2011 - Marea Britanie, Irlanda, SUA - Animaţie, Comedie, Familie Cu: Kyla Rae Kowalewski, Hugo Harold-Harrison Nota: 8.8 / Imdb 8.4",
            "15:50 - Uimitoarea lume a lui Gumball • Ep.1 2011 - Marea Britanie, Irlanda, SUA - Animaţie, Comedie, Familie Cu: Kyla Rae Kowalewski, Hugo Harold-Harrison Nota: 8.8 / Imdb 8.4",
            "16:05 - Uimitoarea lume a lui Gumball • Ep.1 2011 - Marea Britanie, Irlanda, SUA - Animaţie, Comedie, Familie Cu: Kyla Rae Kowalewski, Hugo Harold-Harrison Nota: 8.8 / Imdb 8.4",
            "16:15 - Uimitoarea lume a lui Gumball • Ep.1 2011 - Marea Britanie, Irlanda, SUA - Animaţie, Comedie, Familie Cu: Kyla Rae Kowalewski, Hugo Harold-Harrison Nota: 8.8 / Imdb 8.4",
            "16:30 - Haideți tineri titani! • Ep.7 2013 - SUA - Acţiune, Animaţie, Comedie Cu: Tara Strong, Hynden Walch Nota: 5.8 / Imdb 5.8",
            "17:00 - Haideți tineri titani! • Ep.8 2013 - SUA - Acţiune, Animaţie, Comedie Cu: Tara Strong, Hynden Walch Nota: 5.8 / Imdb 5.8",
            "17:20 - Minunata și năstrușnica lume a lui Gumball • Ep.1",
            "17:35 - Minunata și năstrușnica lume a lui Gumball • Ep.1",
            "17:50 - Lana Barbălungă • Ep.1",
            "18:00 - Lana Barbălungă • Ep.1",
            "18:20 - Clarence • Ep.1 2013 - SUA - Animaţie, Comedie, Familie Cu: Anastasia James, Damien C. Haas Nota: 6.9 / Imdb 6.9",
            "18:25 - Clarence • Ep.1 2013 - SUA - Animaţie, Comedie, Familie Cu: Anastasia James, Damien C. Haas Nota: 6.9 / Imdb 6.9",
            "18:45 - Clarence • Ep.2 2013 - SUA - Animaţie, Comedie, Familie Cu: Anastasia James, Damien C. Haas Nota: 6.9 / Imdb 6.9",
            "18:55 - Clarence • Ep.2 2013 - SUA - Animaţie, Comedie, Familie Cu: Anastasia James, Damien C. Haas Nota: 6.9 / Imdb 6.9",
            "19:10 - Minunata și năstrușnica lume a lui Gumball • Ep.1",
            "19:25 - Minunata și năstrușnica lume a lui Gumball • Ep.1",
            "19:40 - Uimitoarea lume a lui Gumball • Ep.5 2011 - Marea Britanie, Irlanda, SUA - Animaţie, Comedie, Familie Cu: Kyla Rae Kowalewski, Hugo Harold-Harrison Nota: 8.8 / Imdb 8.4",
            "19:50 - Uimitoarea lume a lui Gumball • Ep.5 2011 - Marea Britanie, Irlanda, SUA - Animaţie, Comedie, Familie Cu: Kyla Rae Kowalewski, Hugo Harold-Harrison Nota: 8.8 / Imdb 8.4",
            "20:00 - Uimitoarea lume a lui Gumball • Ep.5 2011 - Marea Britanie, Irlanda, SUA - Animaţie, Comedie, Familie Cu: Kyla Rae Kowalewski, Hugo Harold-Harrison Nota: 8.8 / Imdb 8.4",
            "20:10 - Uimitoarea lume a lui Gumball • Ep.5 2011 - Marea Britanie, Irlanda, SUA - Animaţie, Comedie, Familie Cu: Kyla Rae Kowalewski, Hugo Harold-Harrison Nota: 8.8 / Imdb 8.4",
            "20:30 - Haideți tineri titani! • Ep.3 2013 - SUA - Acţiune, Animaţie, Comedie Cu: Tara Strong, Hynden Walch Nota: 5.8 / Imdb 5.8",
            "20:40 - Haideți tineri titani! • Ep.3 2013 - SUA - Acţiune, Animaţie, Comedie Cu: Tara Strong, Hynden Walch Nota: 5.8 / Imdb 5.8",
            "20:55 - Haideți tineri titani! • Ep.3 2013 - SUA - Acţiune, Animaţie, Comedie Cu: Tara Strong, Hynden Walch Nota: 5.8 / Imdb 5.8",
            "21:05 - Haideți tineri titani! • Ep.3 2013 - SUA - Acţiune, Animaţie, Comedie Cu: Tara Strong, Hynden Walch Nota: 5.8 / Imdb 5.8",
            "21:20 - Minunata și năstrușnica lume a lui Gumball • Ep.1",
            "21:30 - Minunata și năstrușnica lume a lui Gumball • Ep.1",
            "21:50 - Uimitoarea lume a lui Gumball • Ep.5 2011 - Marea Britanie, Irlanda, SUA - Animaţie, Comedie, Familie Cu: Kyla Rae Kowalewski, Hugo Harold-Harrison Nota: 8.8 / Imdb 8.4",
            "22:00 - Uimitoarea lume a lui Gumball • Ep.4 2011 - Marea Britanie, Irlanda, SUA - Animaţie, Comedie, Familie Cu: Kyla Rae Kowalewski, Hugo Harold-Harrison Nota: 8.8 / Imdb 8.4",
            "22:10 - Uimitoarea lume a lui Gumball • Ep.4 2011 - Marea Britanie, Irlanda, SUA - Animaţie, Comedie, Familie Cu: Kyla Rae Kowalewski, Hugo Harold-Harrison Nota: 8.8 / Imdb 8.4",
            "22:30 - Să-nceapă aventura! • Ep.2",
            "22:40 - Să-nceapă aventura! • Ep.2",
            "22:55 - Un show obişnuit • Ep.3 2009 - SUA - Acţiune, Animaţie, Aventuri Cu: Courtenay Taylor, J.G. Quintel Nota: 9.0 / Imdb 8.6",
            "23:05 - Un show obişnuit • Ep.3 2009 - SUA - Acţiune, Animaţie, Aventuri Cu: Courtenay Taylor, J.G. Quintel Nota: 9.0 / Imdb 8.6",
            "23:25 - Minunata și năstrușnica lume a lui Gumball • Ep.1",
            "23:35 - Minunata și năstrușnica lume a lui Gumball • Ep.1",
            "23:50 - Uimitoarea lume a lui Gumball • Ep.1 2011 - Marea Britanie, Irlanda, SUA - Animaţie, Comedie, Familie Cu: Kyla Rae Kowalewski, Hugo Harold-Harrison Nota: 8.8 / Imdb 8.4",
            "00:00 - Uimitoarea lume a lui Gumball • Ep.1 2011 - Marea Britanie, Irlanda, SUA - Animaţie, Comedie, Familie Cu: Kyla Rae Kowalewski, Hugo Harold-Harrison Nota: 8.8 / Imdb 8.4",
            "00:20 - Uimitoarea lume a lui Gumball • Ep.1 2011 - Marea Britanie, Irlanda, SUA - Animaţie, Comedie, Familie Cu: Kyla Rae Kowalewski, Hugo Harold-Harrison Nota: 8.8 / Imdb 8.4",
            "00:30 - Uimitoarea lume a lui Gumball • Ep.1 2011 - Marea Britanie, Irlanda, SUA - Animaţie, Comedie, Familie Cu: Kyla Rae Kowalewski, Hugo Harold-Harrison Nota: 8.8 / Imdb 8.4",
            "00:45 - Uimitoarea lume a lui Gumball • Ep.1 2011 - Marea Britanie, Irlanda, SUA - Animaţie, Comedie, Familie Cu: Kyla Rae Kowalewski, Hugo Harold-Harrison Nota: 8.8 / Imdb 8.4",
            "00:55 - Uimitoarea lume a lui Gumball • Ep.1 2011 - Marea Britanie, Irlanda, SUA - Animaţie, Comedie, Familie Cu: Kyla Rae Kowalewski, Hugo Harold-Harrison Nota: 8.8 / Imdb 8.4",
            "01:05 - Uimitoarea lume a lui Gumball • Ep.1 2011 - Marea Britanie, Irlanda, SUA - Animaţie, Comedie, Familie Cu: Kyla Rae Kowalewski, Hugo Harold-Harrison Nota: 8.8 / Imdb 8.4",
            "01:25 - Uimitoarea lume a lui Gumball • Ep.1 2011 - Marea Britanie, Irlanda, SUA - Animaţie, Comedie, Familie Cu: Kyla Rae Kowalewski, Hugo Harold-Harrison Nota: 8.8 / Imdb 8.4",
            "01:35 - Uimitoarea lume a lui Gumball • Ep.1 2011 - Marea Britanie, Irlanda, SUA - Animaţie, Comedie, Familie Cu: Kyla Rae Kowalewski, Hugo Harold-Harrison Nota: 8.8 / Imdb 8.4",
            "01:50 - Uimitoarea lume a lui Gumball • Ep.1 2011 - Marea Britanie, Irlanda, SUA - Animaţie, Comedie, Familie Cu: Kyla Rae Kowalewski, Hugo Harold-Harrison Nota: 8.8 / Imdb 8.4",
            "02:00 - Uimitoarea lume a lui Gumball • Ep.1 2011 - Marea Britanie, Irlanda, SUA - Animaţie, Comedie, Familie Cu: Kyla Rae Kowalewski, Hugo Harold-Harrison Nota: 8.8 / Imdb 8.4",
            "02:10 - Uimitoarea lume a lui Gumball • Ep.1 2011 - Marea Britanie, Irlanda, SUA - Animaţie, Comedie, Familie Cu: Kyla Rae Kowalewski, Hugo Harold-Harrison Nota: 8.8 / Imdb 8.4",
            "02:25 - Uimitoarea lume a lui Gumball • Ep.1 2011 - Marea Britanie, Irlanda, SUA - Animaţie, Comedie, Familie Cu: Kyla Rae Kowalewski, Hugo Harold-Harrison Nota: 8.8 / Imdb 8.4",
            "02:35 - Uimitoarea lume a lui Gumball • Ep.1 2011 - Marea Britanie, Irlanda, SUA - Animaţie, Comedie, Familie Cu: Kyla Rae Kowalewski, Hugo Harold-Harrison Nota: 8.8 / Imdb 8.4",
            "02:50 - Uimitoarea lume a lui Gumball • Ep.4 2011 - Marea Britanie, Irlanda, SUA - Animaţie, Comedie, Familie Cu: Kyla Rae Kowalewski, Hugo Harold-Harrison Nota: 8.8 / Imdb 8.4",
            "03:00 - Uimitoarea lume a lui Gumball • Ep.4 2011 - Marea Britanie, Irlanda, SUA - Animaţie, Comedie, Familie Cu: Kyla Rae Kowalewski, Hugo Harold-Harrison Nota: 8.8 / Imdb 8.4",
            "03:15 - Uimitoarea lume a lui Gumball • Ep.4 2011 - Marea Britanie, Irlanda, SUA - Animaţie, Comedie, Familie Cu: Kyla Rae Kowalewski, Hugo Harold-Harrison Nota: 8.8 / Imdb 8.4",
            "03:25 - Uimitoarea lume a lui Gumball • Ep.4 2011 - Marea Britanie, Irlanda, SUA - Animaţie, Comedie, Familie Cu: Kyla Rae Kowalewski, Hugo Harold-Harrison Nota: 8.8 / Imdb 8.4",
            "03:35 - Uimitoarea lume a lui Gumball • Ep.4 2011 - Marea Britanie, Irlanda, SUA - Animaţie, Comedie, Familie Cu: Kyla Rae Kowalewski, Hugo Harold-Harrison Nota: 8.8 / Imdb 8.4",
            "03:45 - Uimitoarea lume a lui Gumball • Ep.4 2011 - Marea Britanie, Irlanda, SUA - Animaţie, Comedie, Familie Cu: Kyla Rae Kowalewski, Hugo Harold-Harrison Nota: 8.8 / Imdb 8.4",
            "03:55 - Uimitoarea lume a lui Gumball • Ep.4 2011 - Marea Britanie, Irlanda, SUA - Animaţie, Comedie, Familie Cu: Kyla Rae Kowalewski, Hugo Harold-Harrison Nota: 8.8 / Imdb 8.4",
            "04:05 - Uimitoarea lume a lui Gumball • Ep.4 2011 - Marea Britanie, Irlanda, SUA - Animaţie, Comedie, Familie Cu: Kyla Rae Kowalewski, Hugo Harold-Harrison Nota: 8.8 / Imdb 8.4",
            "04:20 - Uimitoarea lume a lui Gumball • Ep.4 2011 - Marea Britanie, Irlanda, SUA - Animaţie, Comedie, Familie Cu: Kyla Rae Kowalewski, Hugo Harold-Harrison Nota: 8.8 / Imdb 8.4",
            "04:30 - Uimitoarea lume a lui Gumball • Ep.4 2011 - Marea Britanie, Irlanda, SUA - Animaţie, Comedie, Familie Cu: Kyla Rae Kowalewski, Hugo Harold-Harrison Nota: 8.8 / Imdb 8.4",
            "04:40 - Uimitoarea lume a lui Gumball • Ep.4 2011 - Marea Britanie, Irlanda, SUA - Animaţie, Comedie, Familie Cu: Kyla Rae Kowalewski, Hugo Harold-Harrison Nota: 8.8 / Imdb 8.4",
            "04:50 - Uimitoarea lume a lui Gumball • Ep.1 2011 - Marea Britanie, Irlanda, SUA - Animaţie, Comedie, Familie Cu: Kyla Rae Kowalewski, Hugo Harold-Harrison Nota: 8.8 / Imdb 8.4",
            "05:00 - Uimitoarea lume a lui Gumball • Ep.1 2011 - Marea Britanie, Irlanda, SUA - Animaţie, Comedie, Familie Cu: Kyla Rae Kowalewski, Hugo Harold-Harrison Nota: 8.8 / Imdb 8.4",
            "05:10 - Uimitoarea lume a lui Gumball • Ep.1 2011 - Marea Britanie, Irlanda, SUA - Animaţie, Comedie, Familie Cu: Kyla Rae Kowalewski, Hugo Harold-Harrison Nota: 8.8 / Imdb 8.4",
            "05:20 - Uimitoarea lume a lui Gumball • Ep.1 2011 - Marea Britanie, Irlanda, SUA - Animaţie, Comedie, Familie Cu: Kyla Rae Kowalewski, Hugo Harold-Harrison Nota: 8.8 / Imdb 8.4",
            "05:35 - Uimitoarea lume a lui Gumball • Ep.1 2011 - Marea Britanie, Irlanda, SUA - Animaţie, Comedie, Familie Cu: Kyla Rae Kowalewski, Hugo Harold-Harrison Nota: 8.8 / Imdb 8.4",
            "05:45 - Uimitoarea lume a lui Gumball • Ep.1 2011 - Marea Britanie, Irlanda, SUA - Animaţie, Comedie, Familie Cu: Kyla Rae Kowalewski, Hugo Harold-Harrison Nota: 8.8 / Imdb 8.4",
            "05:55 - Uimitoarea lume a lui Gumball • Ep.1 2011 - Marea Britanie, Irlanda, SUA - Animaţie, Comedie, Familie Cu: Kyla Rae Kowalewski, Hugo Harold-Harrison Nota: 8.8 / Imdb 8.4",
            "06:05 - Uimitoarea lume a lui Gumball • Ep.1 2011 - Marea Britanie, Irlanda, SUA - Animaţie, Comedie, Familie Cu: Kyla Rae Kowalewski, Hugo Harold-Harrison Nota: 8.8 / Imdb 8.4",
            "06:15 - Uimitoarea lume a lui Gumball • Ep.1 2011 - Marea Britanie, Irlanda, SUA - Animaţie, Comedie, Familie Cu: Kyla Rae Kowalewski, Hugo Harold-Harrison Nota: 8.8 / Imdb 8.4",
            "06:25 - Uimitoarea lume a lui Gumball • Ep.1 2011 - Marea Britanie, Irlanda, SUA - Animaţie, Comedie, Familie Cu: Kyla Rae Kowalewski, Hugo Harold-Harrison Nota: 8.8 / Imdb 8.4",
            "06:35 - Uimitoarea lume a lui Gumball • Ep.1 2011 - Marea Britanie, Irlanda, SUA - Animaţie, Comedie, Familie Cu: Kyla Rae Kowalewski, Hugo Harold-Harrison Nota: 8.8 / Imdb 8.4",
            "06:45 - Uimitoarea lume a lui Gumball • Ep.1 2011 - Marea Britanie, Irlanda, SUA - Animaţie, Comedie, Familie Cu: Kyla Rae Kowalewski, Hugo Harold-Harrison Nota: 8.8 / Imdb 8.4"
        ]
    },
    {
        "id": 44,
        "tv_channel": "DISCOVERY-CHANNEL",
        "tv_program": [
            "07:00 - Viteză la dublu Sezonul 1 - Episodul 2 - Din nou pe traseu",
            "08:00 - Cum se fabrică ? Sezonul 17 - Episodul 1 - Sombrero-uri decorative/Sosuri de salată/Pistoale cu capse/Medicină regenerativă",
            "08:30 - Cum se fabrică ? Sezonul 17 - Episodul 2 - Răzătoare pentru brânză/Sosuri picante/Bijuterii de argint/Scaune mexicane",
            "09:00 - Căutătorii de opal din Australia Sezonul 7 - Episodul 17 - Școala pietrelor tari",
            "10:00 - Test de supravieţuire în doi Sezonul 9 - Episodul 11 - Frumusețea și bestiile",
            "11:00 - Comori arhitecturale recuperate Sezonul 14 - Episodul 11",
            "12:00 - Maşini pe alese Sezonul 15 - Episodul 12",
            "13:00 - Garajul lui Kindig Sezonul 9 - Episodul 16 - O mașină mortală",
            "14:00 - Test de supravieţuire în doi Sezonul 1 - Episodul 15 - Criză în Botswana",
            "15:00 - Test de supravieţuire în doi Sezonul 1 - Episodul 16 - Foc în munți",
            "16:00 - Comori arhitecturale recuperate Sezonul 17 - Episodul 8",
            "17:00 - Fraţii Diesel: Momente de relaxare Sezonul 1 - Episodul 11 - Căpitanul Sean Dwyer contra RJ Anderson",
            "17:30 - Fraţii Diesel: Momente de relaxare Sezonul 1 - Episodul 12 - Capt. Sean Dwyer contra Wee Man",
            "18:00 - Maşini pe alese Sezonul 12 - Episodul 2 - Ford F100 - Seattle",
            "19:00 - Cum se fabrică ? Sezonul 10 - Episodul 3 - Nivele cu bulă/Hot dog/Granule abrazive/Şmirghel",
            "19:30 - Cum se fabrică ? Sezonul 10 - Episodul 4 - Îngheţată/Crose de golf din lemn/Aripi de avion",
            "20:00 - Test de supraviețuire: Apocalipsa Sezonul 1 - Episodul 1 - Începem cu sfârșitul lumii",
            "22:00 - Test de supravieţuire în doi Sezonul 5 - Episodul 11 - Infern în Honduras",
            "23:00 - Test de supravieţuire: Până la ultimul om Sezonul 3 - Episodul 5 - Strategii sălbatice",
            "01:00 - Comori arhitecturale recuperate Sezonul 9 - Episodul 11",
            "02:00 - Test de supraviețuire: Apocalipsa Sezonul 1 - Episodul 1 - Începem cu sfârșitul lumii",
            "03:36 - Test de supravieţuire în doi Sezonul 5 - Episodul 11 - Infern în Honduras",
            "04:24 - Maşini pe alese Sezonul 14 - Episodul 17 - Un International Scout din 1970",
            "05:12 - Comori arhitecturale recuperate Sezonul 14 - Episodul 2",
            "06:00 - Frații Diesel - Momente de relaxare",
            "06:30 - Frații Diesel - Momente de relaxare"
        ]
    },
    {
        "id": 44,
        "tv_channel": "VIA-HIS",
        "tv_program": [
            "07:00 - Istoria interzisă • Sez.7, Ep.6",
            "08:00 - Titanii Războiului Rece • Sez.2, Ep.4",
            "09:05 - Apocalipsele antichității • Sez.3, Ep.3",
            "10:15 - Alexandru cel Mare: Cuceritorul legendar • Sez.1, Ep.3",
            "11:15 - Secretele ascunse ale Adriaticii • Sez.1, Ep.3",
            "12:15 - Al Doilea Război Mondial: Momente decisive • Sez.1, Ep.3",
            "13:20 - Al Doilea Război Mondial: Prețul Imperiului • Sez.1, Ep.2",
            "14:25 - Titanii Războiului Rece • Sez.2, Ep.4",
            "15:35 - Apocalipsele antichității • Sez.3, Ep.3",
            "16:40 - Alexandru cel Mare: Cuceritorul legendar • Sez.1, Ep.3",
            "17:40 - Secretele ascunse ale Adriaticii • Sez.1, Ep.3",
            "18:40 - Al Doilea Război Mondial: Momente decisive • Sez.1, Ep.3",
            "19:50 - Al Doilea Război Mondial: Prețul Imperiului • Sez.1, Ep.2",
            "20:55 - Titanii Războiului Rece • Sez.2, Ep.4",
            "22:00 - Vikingii: Povestea adevărată • Sez.1, Ep.2",
            "23:00 - Faraonii negri • Ep.2",
            "00:10 - Mongolia lui Ginghis Han • Sez.1, Ep.3",
            "01:10 - Arme secrete: Al Doilea Război Mondial • Sez.1, Ep.1",
            "02:15 - Al Doilea Război Mondial: Prețul Imperiului • Sez.1, Ep.2",
            "03:20 - Al Doilea Război Mondial: Momente decisive • Sez.1, Ep.3",
            "04:30 - Al Doilea Război Mondial: Bătălii pentru Europa • Sez.1, Ep.7",
            "05:45 - Istoria interzisă • Sez.7, Ep.4"
        ]
    },
    {
        "id": 46,
        "tv_channel": "VIA-EXPLORER",
        "tv_program": [
            "07:00 - Căi ferate imposibile • Sez.1, Ep.3",
            "08:05 - Aurul din Yukon • Sez.2, Ep.5",
            "08:55 - Maeștrii apelor reci • Sez.2, Ep.5",
            "10:00 - Anchetatorii acccidentelor aviatice • Sez.3, Ep.2",
            "11:00 - Căutătorii de aur din Australia • Sez.5, Ep.9",
            "12:00 - Căutătorii de aur din Australia • Sez.5, Ep.10",
            "13:00 - Vânătorii de homari din Australia • Sez.5, Ep.3",
            "13:55 - Căutătorii de aur din Australia • Sez.7, Ep.9",
            "15:00 - Căutătorii de aur din Australia • Sez.7, Ep.10",
            "15:55 - Greșeli inginerești grave • Sez.5, Ep.3",
            "16:55 - Căi ferate imposibile • Sez.2, Ep.3",
            "17:55 - Vânătorii de nestemate de la antipozi • Sez.3, Ep.3",
            "19:00 - Căutătorii de aur din Australia • Sez.8, Ep.9",
            "20:00 - Căutătorii de aur din Australia • Sez.8, Ep.10",
            "20:55 - Căutătorii de aur din Australia • Sez.10, Ep.4",
            "22:00 - Coloșii de cherestea • Sez.1, Ep.3",
            "22:55 - Maeștrii apelor reci • Sez.3, Ep.4",
            "00:00 - Căutătorii de aur din Australia • Sez.8, Ep.1",
            "00:55 - Coloșii de cherestea • Sez.2, Ep.7",
            "01:55 - Anchetatorii acccidentelor aviatice • Sez.3, Ep.2",
            "02:55 - Căutătorii de aur din Australia • Sez.3, Ep.11",
            "03:55 - Căutătorii de aur din Australia • Sez.3, Ep.12",
            "04:50 - Eroii din port • Sez.1, Ep.7",
            "05:50 - Eroii din port • Sez.1, Ep.8"
        ]
    },
    {
        "id": 47,
        "tv_channel": "BBC-EARTH",
        "tv_program": [
            "07:00 - Aventurile lui Anton şi Giovanni în Sicilia • Sez.1, Ep.3",
            "08:10 - Mamifere: Making of • Sez.1, Ep.3",
            "08:20 - Mamifere: Making of • Sez.1, Ep.4",
            "08:35 - Unde se află oamenii sălbatici cu Ben Fogle • Sez.1, Ep.4",
            "09:30 - Sub zero grade • Sez.4, Ep.1",
            "10:30 - Mumii dezvăluite • Sez.1, Ep.6",
            "11:30 - În interiorul fabricii • Sez.8, Ep.6",
            "12:35 - Animale imposibile • Sez.1, Ep.7",
            "13:50 - Aventurile în Spania ale lui Anton şi Giovanni • Sez.1, Ep.1",
            "14:55 - Sub zero grade • Sez.4, Ep.2",
            "15:55 - Unde se află oamenii sălbatici cu Ben Fogle • Sez.2, Ep.1",
            "16:55 - Tutankhamon: viața, moartea și moștenirea sa • Sez.1, Ep.1",
            "18:00 - Tsunamiul de după Crăciun • Sez.1, Ep.3",
            "19:00 - Svalbard: viața pe muchie de cuțit • Sez.1, Ep.10",
            "20:00 - Sub zero grade • Sez.2, Ep.4",
            "21:00 - Unde se află oamenii sălbatici cu Ben Fogle • Sez.7, Ep.1",
            "22:00 - Weekend neînfricat • Sez.1, Ep.1",
            "23:05 - Călătorii incredibile cu Simon Reeve • Sez.1, Ep.3",
            "00:10 - Prognoză fatală • Sez.1, Ep.4",
            "01:20 - Svalbard: viața pe muchie de cuțit • Sez.1, Ep.10",
            "02:30 - Sub zero grade • Sez.2, Ep.4",
            "03:15 - Unde se află oamenii sălbatici cu Ben Fogle • Sez.7, Ep.1",
            "04:05 - Weekend neînfricat • Sez.1, Ep.1",
            "04:55 - Călătorii incredibile cu Simon Reeve • Sez.1, Ep.3",
            "05:45 - Mamifere: Making of • Sez.1, Ep.3",
            "05:55 - Mamifere: Making of • Sez.1, Ep.4",
            "06:10 - Svalbard: viața pe muchie de cuțit • Sez.1, Ep.10"
        ]
    },
    {
        "id": 50,
        "tv_channel": "Rock TV",
        "tv_program": [
            "07:00 - We Will Rock You",
            "10:00 - Rockaholic",
            "19:00 - Rock This Way",
            "00:00 - Hard Nights",
            "06:00 - Morning Glory"
        ]
    },
    {
        "id": 51,
        "tv_channel": "Canal32",
        "tv_program": []
    },
    {
        "id": 52,
        "tv_channel": "Magic TV",
        "tv_program": [
            "07:00 - MAGIC START",
            "10:00 - Magic Music at Work",
            "13:00 - Magic Afternoon Coffee",
            "16:00 - Magic Drive Music",
            "19:00 - Magic Music - The Best Music Variety!",
            "22:00 - Magic Night Hits",
            "06:00 - Magic Music - The Best Music Variety!"
        ]
    },
    {
        "id": 55,
        "tv_channel": "CBS News",
        "tv_program": []
    },
    {
        "id": 56,
        "tv_channel": "DigiSport 1",
        "tv_program": [
            "07:20 - Stirile Digi Sport",
            "07:40 - Stirile Digi Sport",
            "08:00 - Stirile Digi Sport",
            "08:20 - Stirile Digi Sport",
            "08:40 - Stirile Digi Sport",
            "09:00 - Stirile Digi Sport",
            "09:20 - Stirile Digi Sport",
            "09:40 - Stirile Digi Sport",
            "10:00 - Stirile Digi Sport",
            "10:15 - Euro Fotbal",
            "11:00 - Stirile Digi Sport",
            "11:15 - Europa League: Dinamo Zagreb-FCSB Etapa 7",
            "12:00 - Stirile Digi Sport",
            "12:15 - Europa League: Dinamo Zagreb-FCSB Etapa 7",
            "13:00 - Stirile Digi Sport",
            "13:15 - Euro Fotbal",
            "13:45 - Premiera Europa League: Rezumate Etapa 7",
            "14:30 - Live Stirile Digi Sport",
            "15:00 - Live Liga Digi Sport",
            "16:30 - Live Stirile Digi Sport",
            "17:00 - Live Superliga: Metaloglobus-FC Arges Etapa 23",
            "17:45 - Live Stirile Digi Sport",
            "18:00 - Live Superliga: Metaloglobus-FC Arges Etapa 23",
            "19:00 - Live Fotbal Club",
            "20:00 - Live Superliga: Hermannstadt-Dinamo Etapa 23",
            "20:45 - Live Fotbal Club",
            "21:00 - Live Superliga: Hermannstadt-Dinamo Etapa 23",
            "22:00 - Live Fotbal Club",
            "23:15 - Live Super Avancronica",
            "00:15 - Stirile Digi Sport",
            "00:30 - Fotbal Club",
            "01:45 - Stirile Digi Sport",
            "02:00 - Superliga: Metaloglobus-FC Arges Etapa 23",
            "03:45 - Stirile Digi Sport",
            "04:00 - Superliga: Hermannstadt-Dinamo Etapa 23",
            "05:45 - Fotbal Club"
        ]
    },
    {
        "id": 74,
        "tv_channel": "France24",
        "tv_program": [
            "07:00 - A LA UNE - LE JOURNAL",
            "07:22 - SPORTS VENDREDI",
            "07:30 - A LA UNE - BULLETIN",
            "08:00 - A LA UNE - LE JOURNAL",
            "08:16 - REVUE DE PRESSE",
            "08:21 - REPORTAGE F24",
            "08:30 - A LA UNE - BULLETIN",
            "08:45 - FOCUS",
            "08:51 - SPORTS VENDREDI",
            "09:00 - A LA UNE - LE JOURNAL",
            "09:16 - L'INVITE",
            "09:30 - A LA UNE - BULLETIN",
            "09:45 - FOCUS",
            "09:50 - SPORTS VENDREDI",
            "09:59 - A LA UNE - LE JOURNAL",
            "10:11 - REVUE DE PRESSE",
            "10:16 - AUX AVANT-POSTES",
            "10:45 - PLAN B",
            "10:51 - FOCUS",
            "11:00 - PARIS DIRECT - LE JOURNAL",
            "11:15 - C'EST EN FRANCE",
            "11:30 - PARIS DIRECT - BULLETIN",
            "11:45 - FOCUS",
            "11:50 - SPORTS VENDREDI",
            "12:00 - PARIS DIRECT - LE JOURNAL",
            "12:15 - PAS 2 QUARTIER",
            "12:21 - DANS LES HEBDOS",
            "12:30 - PARIS DIRECT - BULLETIN",
            "12:45 - EN TETE A TETE",
            "13:00 - PARIS DIRECT - LE JOURNAL",
            "13:16 - A L'AFFICHE",
            "13:30 - PARIS DIRECT - BULLETIN",
            "13:45 - FOCUS",
            "13:50 - SPORTS VENDREDI",
            "13:59 - PARIS DIRECT - LE JOURNAL",
            "14:16 - L'INVITE",
            "14:30 - LE JOURNAL - LE CLUB PARIS DIRECT",
            "14:50 - CHRONIQUE ACTUELLES",
            "15:00 - LE JOURNAL - LE CLUB AUTOUR DU MONDE",
            "15:20 - TECH 24",
            "15:30 - AUTOUR DU MONDE - LE JOURNAL",
            "15:45 - CHRONIQUE CULTURE",
            "15:51 - ELEMENT TERRE LA QUOTIDIENNE",
            "16:00 - AUTOUR DU MONDE - LE JOURNAL",
            "16:15 - DANS LES HEBDOS",
            "16:22 - LES OBSERVATEURS",
            "16:30 - AUTOUR DU MONDE - BULLETIN",
            "16:45 - OUTRE-MER",
            "17:00 - AUTOUR DU MONDE - LE JOURNAL",
            "17:15 - ACTUELLES",
            "17:30 - AUTOUR DU MONDE - BULLETIN",
            "17:45 - A L'AFFICHE",
            "18:00 - AUTOUR DU MONDE - LE JOURNAL",
            "18:15 - LA SEMAINE DE L'ECO",
            "18:55 - L'INSTANT MOBILE",
            "18:59 - AU COEUR DE L'INFO - LE JOURNAL",
            "19:15 - EN TETE A TETE",
            "19:29 - AU COEUR DE L'INFO - BULLETIN",
            "19:45 - PAS 2 QUARTIER",
            "19:51 - DANS LES HEBDOS",
            "20:00 - AU COEUR DE L'INFO - LE JOURNAL",
            "20:10 - UNE SEMAINE DANS LE MONDE",
            "20:55 - L'INSTANT MOBILE",
            "21:00 - LE JOURNAL L'INVITE AU COEUR DE L'INFO",
            "21:22 - SPORTS VENDREDI",
            "21:30 - LE MONDE DANS TOUS SES ETATS",
            "22:00 - L'ESSENTIEL - LE JOURNAL",
            "22:15 - ELEMENT TERRE LA QUOTIDIENNE",
            "22:21 - INFO-INTOX",
            "22:30 - L'ESSENTIEL - LE JOURNAL",
            "22:36 - LA QUESTION QUI FACHE",
            "22:44 - LE JOURNAL DE L'AFRIQUE",
            "23:00 - L'ESSENTIEL - LE JOURNAL",
            "23:15 - INFO-INTOX",
            "23:21 - SPORTS VENDREDI",
            "23:30 - L'ESSENTIEL - LE JOURNAL",
            "23:44 - LE JOURNAL DE L'AFRIQUE",
            "00:00 - L'ESSENTIEL - LE JOURNAL",
            "00:10 - LE CAFE DES SPORTS",
            "01:00 - L'ESSENTIEL - LE JOURNAL",
            "01:15 - UNE SEMAINE DANS LE MONDE",
            "02:00 - L'EDITION NUIT - LE JOURNAL",
            "02:14 - LE JOURNAL DE L'AFRIQUE",
            "02:30 - L'EDITION NUIT - BULLETIN",
            "02:45 - A L'AFFICHE",
            "03:00 - L'EDITION NUIT - LE JOURNAL",
            "03:15 - LA SEMAINE DE L'ECO",
            "03:55 - L'INSTANT MOBILE",
            "04:00 - L'EDITION NUIT - LE JOURNAL",
            "04:10 - LE CAFE DES SPORTS",
            "05:00 - L'EDITION NUIT - LE JOURNAL",
            "05:11 - UNE SEMAINE DANS LE MONDE",
            "06:00 - L'EDITION NUIT - LE JOURNAL",
            "06:15 - ACTUELLES",
            "06:30 - L'EDITION NUIT - BULLETIN",
            "06:44 - LE JOURNAL DE L'AFRIQUE"
        ]
    },
    {
        "id": 77,
        "tv_channel": "TVR Sport",
        "tv_program": []
    },
    {
        "id": 78,
        "tv_channel": "Romania TV",
        "tv_program": [
            "07:00 - Ştirile România TV",
            "08:00 - Ştirile România TV",
            "09:00 - Ştirile România TV",
            "10:00 - Ştirile România TV",
            "11:00 - Ştirile România TV",
            "12:00 - Ştirile România TV",
            "13:00 - Ştirile România TV",
            "14:00 - Ştirile România TV",
            "15:00 - Stirile Romania TV",
            "16:00 - Ştirile România TV",
            "17:00 - Ediție specială",
            "18:00 - Ştirile România TV",
            "19:00 - Ediție specială",
            "20:00 - Ediție specială",
            "21:00 - Ediție specială",
            "23:00 - Ştirile România TV",
            "00:00 - Ştirile România TV",
            "01:00 - Ediție specială-19:00",
            "02:00 - Ediție specială-20:00",
            "03:00 - Ediţie specială-21:00",
            "04:00 - Ediţie specială-22:00",
            "05:00 - Ştirile România TV",
            "06:00 - Ştirile România TV"
        ]
    },
    {
        "id": 23,
        "tv_channel": "AMC",
        "tv_program": [
            "08:45 - Căpitanul Phillips 2013 - SUA - Biografic, Crimă, Dramă Cu: Tom Hanks, Barkhad Abdi Nota: 8.3 / Imdb 7.8",
            "11:35 - Mai iute ca moartea 1995 - SUA - Acţiune, Western Cu: Sharon Stone, Leonardo DiCaprio Nota: 7.2 / Imdb 6.5",
            "13:45 - Giuvaierul Nilului 1985 - SUA - Comedie Cu: Michael Douglas, Kathleen Turner Nota: 6.9 / Imdb 6.1",
            "15:55 - Nelegiuiții vestului sălbatic 2001 - SUA - Acţiune, Comedie, Western Cu: Colin Farrell, Scott Caan Nota: 7.0 / Imdb 5.9",
            "17:50 - Şarpele în umbra vulturului 1978 - Hong Kong - Acţiune, Comedie Cu: Jackie Chan, Siu Tin Yuen Nota: 7.9 / Imdb 7.3",
            "20:00 - Tombstone 1993 - SUA - Acţiune, Dramă, Western Cu: Kurt Russell, Val Kilmer Nota: 7.5 / Imdb 7.8",
            "22:45 - Nocturna 2015 - Horror, Thriller Cu: Estella Warren, Mike Doyle Nota: 5.6 / Imdb 3.6",
            "00:45 - Joc în doi 1997 - SUA - Acţiune Cu: Jean-Claude Van Damme, Dennis Rodman Nota: 6.5 / Imdb 4.8",
            "02:40 - Jocuri, poturi și focuri de armă 1998 - Marea Britanie - Comedie, Dramă Cu: Steven Mackintosh, Nick Moran (I) Nota: 8.3 / Imdb 8.1",
            "04:50 - Close Up • Ep.19 2011 - SUA - Biografic Cu: Angela Valley, Ben Affleck Nota: 6.6 / Imdb 6.5",
            "05:25 - Close Up • Ep.20 2011 - SUA - Biografic Cu: Angela Valley, Ben Affleck Nota: 6.6 / Imdb 6.5",
            "06:00 - Crăciun cu un prinţ: Bebeluşul regal 2021 - Romantic Cu: Nick Hounslow, Josh Dean Nota: - / Imdb 5.7"
        ]
    },
    {
        "id": 91,
        "tv_channel": "DigiSport 2",
        "tv_program": [
            "08:55 - Live Patinaj artistic: Campionatul celor 4 Continente Victory Ceremony Ice Dance",
            "09:15 - Europa League Etapa 7",
            "11:00 - Patinaj artistic: Campionatul celor 4 Continente Ice Dance (Free Dance)",
            "12:00 - Live Patinaj artistic: Campionatul celor 4 Continente Women (Free Skating)",
            "15:50 - Live Patinaj artistic: Campionatul celor 4 Continente Victory Ceremony Women",
            "16:15 - Europa League: Dinamo Zagreb-FCSB Etapa 7",
            "18:15 - Europa League: Rezumate Etapa 7",
            "19:00 - Stirile Digi Sport",
            "19:30 - Live Bundesliga 2: Darmstadt-Nurenberg Etapa 19",
            "21:30 - Stirile Digi Sport",
            "21:45 - Live Serie A: Inter-Pisa Etapa 22",
            "23:45 - Stirile Digi Sport",
            "00:15 - Europa League Etapa 7",
            "02:15 - La Liga: Levante-Elche Etapa 21",
            "04:00 - Serie A: Inter-Pisa Etapa 22",
            "05:45 - Stirile Digi Sport",
            "06:10 - Live Patinaj artistic: Campionatul celor 4 Continente Men (Short Program)"
        ]
    },
    {
        "id": 321,
        "tv_channel": "CineMax",
        "tv_program": [
            "07:00 - Dă-mi o șansă 2023 - Franta - Comedie, Dramă Cu: Louane Emera, Michel Blanc Nota: - / Imdb 6.3",
            "08:40 - Domnul și doamna Smith 2005 - SUA - Acţiune, Comedie, Romantic Cu: Angelina Jolie, Brad Pitt Nota: 7.5 / Imdb 6.5",
            "10:40 - Paprika 2006 - Japonia - Animaţie, Dramă, Fantastic Cu: Megumi Hayashibara, Tôru Furuya Nota: 8.0 / Imdb 7.7",
            "12:10 - Omul de argilă 2023 - Franta - Dramă, Romantic Cu: Raphaël Thierry, Emmanuelle Devos Nota: - / Imdb 6.4",
            "13:45 - Inimi tinere 2024 - Belgia, Olanda - Dramă, Familie Cu: Geert Van Rampelberg, Emilie Deroo Nota: 7.0 / Imdb 7.9",
            "15:25 - Duino 2024 - SUA, Argentina - Dramă, Romantic Cu: Juan Pablo Di Pace, Oscar Morgan Nota: - / Imdb 7.0",
            "17:10 - Domnul și doamna Smith 2005 - SUA - Acţiune, Comedie, Romantic Cu: Angelina Jolie, Brad Pitt Nota: 7.5 / Imdb 6.5",
            "19:10 - Talladega Nights: Balada lui Ricky Bobby 2006 - SUA - Acţiune, Comedie, Sport Cu: Will Ferrell, Greg Germann Nota: 6.7 / Imdb 6.6",
            "22:55 - Operațiunea Mogadishu 2001 - SUA - Dramă, Război Cu: Josh Hartnett, Johnny Strong Nota: 8.3 / Imdb 7.7",
            "01:15 - Poltergeist III 1988 - SUA - Horror, Thriller Cu: Tom Skerritt, Nancy Allen Nota: 6.5 / Imdb 4.7",
            "02:50 - Băieți răi pe viață 2020 - SUA - Acţiune, Comedie, Crimă Cu: Will Smith, Martin Lawrence Nota: 7.6 / Imdb 6.5",
            "04:50 - Ofsaid",
            "05:15 - Cel mai frumos cadou 2022 - Danemarca - Comedie, Dramă Cu: Sofie Torp, Roberta Reichhardt Nota: - / Imdb 5.9"
        ]
    },
    {
        "id": 322,
        "tv_channel": "CineMax2",
        "tv_program": [
            "07:00 - Pasul 9 2022 - Lituania - Dramă Cu: Valentin Novopolskij, Gerda Ciuraite Nota: - / Imdb 6.7",
            "08:35 - Ciuma 2023 - Bulgaria - Dramă Cu: Svezhen Mladenov, Evelina Bibova Nota: - / Imdb 5.9",
            "10:20 - Club Zero 2023 - Austria, Marea Britanie, Germania, Franta, Danemarca, Qatar - Dramă, Thriller Cu: Mia Wasikowska, Sidse Babett Knudsen Nota: 6.7 / Imdb 5.8",
            "12:10 - Solidaritatea fetelor 2023 - Franta, Maroc - Comedie, Dramă Cu: Médina Diarra, Leah Aubert Nota: - / Imdb 6.2",
            "13:50 - O zi fericită 2023 - Norvegia - Comedie, Dramă Cu: Stig Frode Henriksen, Anja Saiva Bongo Bjørnstad Nota: - / Imdb 6.1",
            "15:45 - Juriul 2003 - SUA - Acţiune, Thriller Cu: John Cusack, Gene Hackman Nota: 7.5 / Imdb 7.1",
            "17:55 - Ciuma 2023 - Bulgaria - Dramă Cu: Svezhen Mladenov, Evelina Bibova Nota: - / Imdb 5.9",
            "19:40 - Anul văduvei 2024 - Cehia - Dramă Cu: Tomás Bambusek, Pavla Beretova Nota: - / Imdb 6.0",
            "21:30 - Olmo 2025 - SUA - Comedie, Dramă Cu: Aivan Uttapa, Melanie Frometa Nota: - / Imdb 6.6",
            "22:55 - Corul 2004 - Franta - Dramă, Romantic, Dragoste Cu: Fabrice Dubusset, Gregory Gatignol Nota: 8.5 / Imdb 7.8",
            "00:30 - Vreau să simt 2024 - SUA - Comedie, Romantic, SF Cu: Luke Kirby, Griffin Newman Nota: - / Imdb 5.6",
            "02:10 - Amintirile unui trup ars de dorință 2024 - Costa Rica, Spania - Dramă Cu: Juliana Filloy Bogantes, Leonardo Perucci Nota: - / Imdb 6.5",
            "03:40 - Viață de câine 2023 - Belgia - Comedie, Dramă Cu: Jean-Jacques Rausin, Mara Taquin Nota: - / Imdb 6.4",
            "05:15 - Mai e mult timp până mâine 2023 - Singapore, Taiwan, Franta, Portugalia - Dramă Cu: Leon Dai, Edward Tan Nota: - / Imdb 6.6"
        ]
    },
    {
        "id": 99935,
        "tv_channel": "Viasat-Nature",
        "tv_program": [
            "07:10 - Veterinari bizari • Sez.1, Ep.6",
            "08:00 - Monştrii apelor • Sez.6, Ep.2",
            "08:50 - Monştrii apelor • Sez.6, Ep.3",
            "09:40 - Prădători • Ep.3",
            "10:25 - Istoria zbuciumată a planetei • Sez.1, Ep.4",
            "11:20 - Uriașii • Sez.1, Ep.4",
            "12:15 - Vestul Sălbatic • Sez.1, Ep.2",
            "13:05 - Animalele extraordinare ale Africii • Sez.1, Ep.3",
            "13:55 - Namibia extremă • Sez.1, Ep.1",
            "14:45 - Monştrii apelor • Sez.6, Ep.4",
            "15:35 - Monştrii apelor • Sez.6, Ep.5",
            "16:25 - Istoria zbuciumată a planetei • Sez.1, Ep.4",
            "17:20 - Prădători • Ep.4",
            "18:05 - Uriașii • Sez.1, Ep.5",
            "19:00 - Madagascar: Galapagosul Africii • Ep.5",
            "19:50 - Namibia extremă • Sez.1, Ep.2",
            "20:45 - Vestul Sălbatic • Sez.1, Ep.3",
            "21:35 - Istoria zbuciumată a planetei • Sez.1, Ep.5",
            "22:30 - Prădători • Ep.5",
            "23:15 - Vestul Sălbatic • Sez.1, Ep.3",
            "00:05 - Monştrii apelor • Sez.6, Ep.4",
            "00:55 - Monştrii apelor • Sez.6, Ep.5",
            "01:45 - Uriașii • Sez.1, Ep.5",
            "02:40 - Madagascar: Galapagosul Africii • Ep.5",
            "03:30 - Namibia extremă • Sez.1, Ep.2",
            "04:25 - Monştrii apelor • Sez.6, Ep.4",
            "05:15 - Monştrii apelor • Sez.6, Ep.5",
            "06:05 - Veterinari bizari • Sez.1, Ep.6"
        ]
    },
    {
        "id": 53872,
        "tv_channel": "HBO3",
        "tv_program": [
            "07:00 - Dune: Partea II 2024 - SUA, Canada - Acţiune, Aventuri, Dramă Cu: Rebecca Ferguson, Timothée Chalamet Nota: 8.3 / Imdb 8.4",
            "09:40 - El este Benjamin Ingrosso - Partea a II-a",
            "10:35 - Fetele • Sez.6, Ep.7 2012 - SUA - Comedie Cu: Lena Dunham, Allison Williams Nota: 7.1 / Imdb 7.4",
            "11:00 - Fetele • Sez.6, Ep.8 2012 - SUA - Comedie Cu: Lena Dunham, Allison Williams Nota: 7.1 / Imdb 7.4",
            "11:30 - Julie și Julia 2009 - SUA - Biografic, Comedie, Dramă Cu: Meryl Streep, Amy Adams Nota: 7.5 / Imdb 7.0",
            "13:30 - Ruby Gillman, adolescenta kraken 2023 - SUA - Acţiune, Animaţie, Aventuri Cu: Jane Fonda, Toni Collette Nota: 6.8 / Imdb 5.7",
            "15:00 - Țestoasele Ninja 2007 - SUA - Acţiune, Animaţie, Aventuri Cu: James Arnold Taylor, Mikey Kelley Nota: 7.3 / Imdb 6.2",
            "16:25 - Hacks • Sez.4, Ep.3 2021 - SUA - Comedie, Dramă Cu: Jean Smart, Carl Clemons-Hopkins Nota: 7.3 / Imdb 8.2",
            "16:50 - Hacks • Sez.4, Ep.4 2021 - SUA - Comedie, Dramă Cu: Jean Smart, Carl Clemons-Hopkins Nota: 7.3 / Imdb 8.2",
            "17:25 - Mai mult decât ficțiune 2006 - SUA - Comedie, Dramă, Fantastic Cu: Dustin Hoffman, Emma Thompson Nota: 7.7 / Imdb 7.5",
            "19:15 - Millie Black • Sez.1, Ep.2 2024 - Marea Britanie - Crimă, Dramă Cu: Tamara Lawrance, Joe Dempsie Nota: - / Imdb 6.6",
            "20:30 - Fetele • Sez.6, Ep.10 2012 - SUA - Comedie Cu: Lena Dunham, Allison Williams Nota: 7.1 / Imdb 7.4",
            "21:00 - Succesiunea • Sez.4, Ep.6 2018 - SUA - Dramă Cu: Katie Lee Hill, Peggy J. Scott Nota: 8.0 / Imdb 8.8",
            "22:00 - Cartelul crimelor • Sez.1, Ep.1 2002 - SUA - Dramă Cu: Dominic West, John Doman Nota: 9.0 / Imdb 9.3",
            "23:00 - Cartelul crimelor • Sez.1, Ep.2 2002 - SUA - Dramă Cu: Dominic West, John Doman Nota: 9.0 / Imdb 9.3",
            "23:55 - Cartelul crimelor • Sez.1, Ep.3 2002 - SUA - Dramă Cu: Dominic West, John Doman Nota: 9.0 / Imdb 9.3",
            "00:50 - Cartelul crimelor • Sez.1, Ep.4 2002 - SUA - Dramă Cu: Dominic West, John Doman Nota: 9.0 / Imdb 9.3",
            "01:45 - Cartelul crimelor • Sez.1, Ep.5 2002 - SUA - Dramă Cu: Dominic West, John Doman Nota: 9.0 / Imdb 9.3",
            "02:45 - Cartelul crimelor • Sez.1, Ep.6 2002 - SUA - Dramă Cu: Dominic West, John Doman Nota: 9.0 / Imdb 9.3",
            "03:50 - Cabin Pressure 2024 - Ungaria - Documentar Cu: Henriett Kiss Nota: - / Imdb 6.2",
            "05:10 - Un băiat bun cu o armă 2022 - SUA - Dramă, Thriller Cu: Beck Nolan, Jack Cain Nota: - / Imdb 5.3"
        ]
    },
    {
        "id": 26563,
        "tv_channel": "CineMaraton",
        "tv_program": [
            "07:50 - Medalion / Scurtmetraj / Jurnal / Pastilă",
            "08:00 - Bună seara, Irina 1980 - Romania - Dramă, Romantic Cu: Ștefan Iordache, Valeria Seciu Nota: 7.3 / Imdb 6.7",
            "09:35 - Medalion / Scurtmetraj / Jurnal / Pastilă",
            "09:50 - Vanatoarea",
            "10:01 - Medalion / Scurtmetraj / Jurnal / Pastilă",
            "10:20 - Al patrulea stol 1978 - Romania Cu: Violeta Andrei, Ileana Stana Ionescu Nota: 7.4 / Imdb 7.2",
            "11:55 - Medalion / Scurtmetraj / Jurnal / Pastilă",
            "12:10 - Septembrie 1978 - Romania - Dramă Cu: Anda Onesa, Geo Costiniu Nota: 7.9 / Imdb 7.7",
            "13:55 - Medalion / Scurtmetraj / Jurnal / Pastilă",
            "14:10 - Cursa 1975 - Romania - Dramă Cu: Constantin Diplan, Mircea Albulescu Nota: 7.7 / Imdb 7.5",
            "15:46 - Medalion / Scurtmetraj / Jurnal / Pastilă",
            "16:00 - Păcală 1974 - Romania - Comedie Cu: Mariella Petrescu, Sebastian Papaiani Nota: 8.3 / Imdb 7.6",
            "18:06 - Medalion / Scurtmetraj / Jurnal / Pastilă",
            "18:25 - B.D. intră în acțiune 1970 - Romania - Comedie Cu: Puiu Călinescu, Sebastian Papaiani Nota: 8.9 / Imdb 8.5",
            "20:05 - Medalion / Scurtmetraj / Jurnal / Pastilă",
            "20:20 - B.D. în alertă 1971 - Romania - Comedie Cu: Sebastian Papaiani, Toma Caragiu Nota: 8.9 / Imdb 8.6",
            "21:55 - Medalion / Scurtmetraj / Jurnal / Pastilă",
            "22:15 - B.D. la munte și la mare 1971 - Romania - Comedie Cu: Ion Finteșteanu, Toma Caragiu Nota: 8.9 / Imdb 8.6",
            "23:55 - Medalion / Scurtmetraj / Jurnal / Pastilă",
            "00:10 - Capra cu trei iezi 2022 - Romania - Horror, Thriller Cu: Maia Morgenstern, Marius Bodochi Nota: 7.5 / Imdb 7.2",
            "01:33 - Medalion / Scurtmetraj / Jurnal / Pastilă",
            "01:50 - Orient Express 2004 - Romania - Dramă Cu: Maia Morgenstern, Sergiu Nicolaescu Nota: 7.2 / Imdb 6.1",
            "03:45 - Medalion / Scurtmetraj / Jurnal / Pastilă",
            "04:05 - Patul lui Procust 2001 - Moldova - Dramă, Romantic, Dragoste Cu: Maia Morgenstern, Petru Vutcărău Nota: 8.1 / Imdb 7.5",
            "06:02 - Medalion / Scurtmetraj / Jurnal / Pastilă",
            "06:20 - Marea sfidare 1989 - Dramă Cu: Maia Morgenstern, Victoria Cociaș Nota: 7.1 / Imdb 7.1"
        ]
    }
]